{
  "status": "complete",
  "version": 1,
  "timestamp": "2025-01-14T12:00:00.000Z",
  "files_written": [
    "prompts/app_spec.txt",
    "prompts/initializer_prompt.md"
  ],
  "feature_count": 280,
  "phases": {
    "phase_1": {
      "name": "Core MVP",
      "feature_count": 140,
      "description": "Core functionality with basic brand templates, Stripe billing, professional PDF export, and essential E2E tests"
    },
    "phase_2": {
      "name": "Advanced Features",
      "feature_count": 140,
      "description": "YOLO mode, advanced brand templates, institution features, template versioning, enhanced macros, onboarding, and comprehensive E2E tests"
    }
  }
}
